{
  "annotations": {
    "list": [
      {
        "builtIn": 1,
        "datasource": "-- Grafana --",
        "enable": true,
        "hide": true,
        "iconColor": "rgba(0, 211, 255, 1)",
        "name": "Annotations & Alerts",
        "type": "dashboard"
      }
    ]
  },
  "editable": true,
  "gnetId": null,
  "graphTooltip": 0,
  "id": null,
  "links": [],
  "panels": [
    {
      "datasource": "Prometheus",
      "fieldConfig": {
        "defaults": {
          "color": {
            "mode": "palette-classic"
          },
          "custom": {
            "axisLabel": "",
            "axisPlacement": "auto",
            "barAlignment": 0,
            "drawStyle": "line",
            "fillOpacity": 10,
            "gradientMode": "none",
            "hideFrom": {
              "tooltip": false,
              "viz": false,
              "legend": false
            },
            "lineInterpolation": "linear",
            "lineWidth": 1,
            "pointSize": 5,
            "scaleDistribution": {
              "type": "linear"
            },
            "showPoints": "never",
            "spanNulls": true
          },
          "mappings": [],
          "thresholds": {
            "mode": "absolute",
            "steps": [
              {
                "color": "green",
                "value": null
              },
              {
                "color": "red",
                "value": 80
              }
            ]
          },
          "unit": "short"
        },
        "overrides": []
      },
      "gridPos": {
        "h": 8,
        "w": 12,
        "x": 0,
        "y": 0
      },
      "id": 1,
      "options": {
        "tooltip": {
          "mode": "single"
        },
        "legend": {
          "calcs": [],
          "displayMode": "list",
          "placement": "bottom"
        }
      },
      "pluginVersion": "8.0.0",
      "targets": [
        {
          "expr": "rate(security_threats_total[5m])",
          "format": "time_series",
          "intervalFactor": 1,
          "refId": "A",
          "legendFormat": "{{type}}"
        }
      ],
      "title": "Security Threats by Type",
      "type": "timeseries"
    },
    {
      "datasource": "Prometheus",
      "fieldConfig": {
        "defaults": {
          "color": {
            "mode": "thresholds"
          },
          "mappings": [],
          "thresholds": {
            "mode": "absolute",
            "steps": [
              {
                "color": "green",
                "value": null
              },
              {
                "color": "yellow",
                "value": 100
              },
              {
                "color": "red",
                "value": 500
              }
            ]
          },
          "unit": "short"
        },
        "overrides": []
      },
      "gridPos": {
        "h": 8,
        "w": 6,
        "x": 12,
        "y": 0
      },
      "id": 2,
      "options": {
        "orientation": "auto",
        "reduceOptions": {
          "values": false,
          "calcs": [
            "lastNotNull"
          ],
          "fields": ""
        },
        "showThresholdLabels": false,
        "showThresholdMarkers": true,
        "text": {}
      },
      "pluginVersion": "8.0.0",
      "targets": [
        {
          "expr": "sum(rate(rate_limit_exceeded_total[5m]))",
          "format": "time_series",
          "intervalFactor": 1,
          "refId": "A"
        }
      ],
      "title": "Rate Limit Violations",
      "type": "gauge"
    },
    {
      "datasource": "Prometheus",
      "fieldConfig": {
        "defaults": {
          "color": {
            "mode": "thresholds"
          },
          "mappings": [],
          "thresholds": {
            "mode": "absolute",
            "steps": [
              {
                "color": "green",
                "value": null
              },
              {
                "color": "red",
                "value": 1
              }
            ]
          },
          "unit": "short"
        },
        "overrides": []
      },
      "gridPos": {
        "h": 8,
        "w": 6,
        "x": 18,
        "y": 0
      },
      "id": 3,
      "options": {
        "colorMode": "value",
        "graphMode": "none",
        "justifyMode": "auto",
        "orientation": "auto",
        "reduceOptions": {
          "values": false,
          "calcs": [
            "lastNotNull"
          ],
          "fields": ""
        },
        "text": {},
        "textMode": "auto"
      },
      "pluginVersion": "8.0.0",
      "targets": [
        {
          "expr": "sum(increase(security_threats_total{type=\"sql_injection\"}[24h]))",
          "format": "time_series",
          "intervalFactor": 1,
          "refId": "A"
        }
      ],
      "title": "SQL Injection Attempts (24h)",
      "type": "stat"
    }
  ],
  "refresh": "5s",
  "schemaVersion": 27,
  "style": "dark",
  "tags": ["security"],
  "templating": {
    "list": []
  },
  "time": {
    "from": "now-6h",
    "to": "now"
  },
  "timepicker": {},
  "timezone": "",
  "title": "AskProAI Security Dashboard",
  "uid": "askproai-security",
  "version": 0
}